ohlcutils/__init__.py
ohlcutils/_arg_validators.py
ohlcutils/charting.py
ohlcutils/config.py
ohlcutils/data.py
ohlcutils/enums.py
ohlcutils/indicators.py
ohlcutils/testing.py
ohlcutils/config/config_sample.yaml
ohlcutils-0.1.14.dist-info/METADATA
ohlcutils-0.1.14.dist-info/WHEEL
ohlcutils-0.1.14.dist-info/top_level.txt
ohlcutils-0.1.14.dist-info/RECORD
