Metadata-Version: 2.4
Name: ohlcutils
Version: 0.1.14
Summary: A lightweight Python library for python utilities for holidays, dates, options and other tools
Author-email: Pankaj Sharma <sharma.pankaj.kumar@gmail.com>
License-Expression: MIT
Project-URL: homepage, https://bitbucket.org/incurrency/ohlcutils
Project-URL: repository, https://bitbucket.org/incurrency/ohlcutils
Requires-Dist: chameli
Requires-Dist: pandas-ta==0.3.14b0
Requires-Dist: plotly==6.1.0
Requires-Dist: nbformat==5.10.4
